[
  { "id": "b3c4d5e6-f708-4910-a1b2-c3d4e5f6a711", "data": [ { "text": "有试听课吗？", "userDefined": false } ], "isTemplate": false, "lang": "zh-cn", "updated": 0 },
  { "id": "c4d5e6f7-0819-4a12-b2c3-d4e5f6a7b812", "data": [ { "text": "可以先试一节课吗？", "userDefined": false } ], "isTemplate": false, "lang": "zh-cn", "updated": 0 },

  { "id": "0456789a-bcde-4234-0567-89abcdef1206", "data": [ { "text": "有免费试听吗？", "userDefined": false } ], "lang": "zh-cn", "isTemplate": false, "updated": 0 },
  { "id": "156789ab-cdef-4345-1678-9abcdef12307", "data": [ { "text": "怎么预约试听？", "userDefined": false } ], "lang": "zh-cn", "isTemplate": false, "updated": 0 }
]