{"metadataAttributes":{"language":{"value":{"type":"STRING","stringValue":"en"},"includeForEmbedding":true},"type":{"value":{"type":"STRING","stringValue":"faq"},"includeForEmbedding":true},"canonical":{"value":{"type":"STRING","stringValue":"HomeworkPolicy"},"includeForEmbedding":true},"folder":{"value":{"type":"STRING","stringValue":"faq"},"includeForEmbedding":true},"aliases":{"value":{"type":"STRING","stringValue":"homework; reading; writing; time needed; duration; K1; P1; 作业; 功課"},"includeForEmbedding":true}}}